spamming/__init__.py
spamming-0.1.3.dist-info/LICENSE
spamming-0.1.3.dist-info/METADATA
spamming-0.1.3.dist-info/WHEEL
spamming-0.1.3.dist-info/top_level.txt
spamming-0.1.3.dist-info/RECORD
