Metadata-Version: 2.1
Name: spamming
Version: 0.1.3
Summary: A spamming package
Author: gugu256
Author-email: gugu256@mail.com
License: MIT
Keywords: spamming,spam,automation,pyautogui
Classifier: Development Status :: 5 - Production/Stable
Classifier: Programming Language :: Python :: 3
Classifier: Operating System :: Unix
Classifier: Operating System :: MacOS :: MacOS X
Classifier: Operating System :: Microsoft :: Windows
License-File: LICENSE
Requires-Dist: pyautogui
